AUTHORS.rst
CONTRIBUTING.rst
HISTORY.rst
LICENSE
MANIFEST.in
README.rst
setup.py
yo_payments/__init__.py
yo_payments.egg-info/PKG-INFO
yo_payments.egg-info/SOURCES.txt
yo_payments.egg-info/dependency_links.txt
yo_payments.egg-info/not-zip-safe
yo_payments.egg-info/pbr.json
yo_payments.egg-info/requires.txt
yo_payments.egg-info/top_level.txt