Metadata-Version: 1.1
Name: yo-payments
Version: 0.1.6
Summary: Python Api Wrapper for the Yo Payments service
Home-page: https://github.com/jamesmura/yo_payments
Author: James Muranga
Author-email: jmured@gmail.com
License: MIT
Keywords: yo_payments
Platform: UNKNOWN
Classifier: Development Status :: 2 - Pre-Alpha
Classifier: Intended Audience :: Developers
Classifier: License :: OSI Approved :: MIT License
Classifier: Natural Language :: English
Classifier: Programming Language :: Python :: 2.7
Classifier: Programming Language :: Python :: 3.4
